{
  "venue_id": 4838,
  "venue_slug": "mariscos-la-riviera-nayarit",
  "meta": {
    "og_image": "https://static-content.owner.com/funnel/images/036e87ee-a7da-4081-a1ef-633bebb6ca64?v=9956117309",
    "meta_description": "Mariscos La Riviera Nayarit Official Website. Save Money Ordering Directly Here. Healthy Options. Fast Service. Friendly Team. Top Rated.",
    "reservation_links": [],
    "menu_links": [
      "https://mariscoslarivieranayaritga.com/mariscoslarivieranayarit-norcross?utm_source=google/menu/mariscoslarivieranayarit-norcross"
    ],
    "instagram": "mariscoslarivieranayarit",
    "facebook_url": "https://facebook.com/mariscoslarivieranayaritoficial",
    "phone": "(770) 662-0086"
  },
  "extracted": {
    "hours": {
      "mon": {"open": "10:00", "close": "22:00"},
      "tue": {"open": "10:00", "close": "22:00"},
      "wed": {"open": "10:00", "close": "22:00"},
      "thu": {"open": "10:00", "close": "22:00"},
      "fri": {"open": "10:00", "close": "23:00"},
      "sat": {"open": "10:00", "close": "23:00"},
      "sun": {"open": "10:00", "close": "22:00"}
    },
    "vibes": ["lively", "family-friendly", "good-for-groups", "outdoor-seating"],
    "cuisine": ["mexican", "seafood"],
    "service_style": "casual_dine_in",
    "price_level": 2,
    "menu_highlights": [
      {"name": "Huachinango a La Riviera", "price": "$28.99", "category": "entree"},
      {"name": "Camarones Koras", "price": "$27.99", "category": "entree"},
      {"name": "Langostinos", "price": "$39.99", "category": "entree"},
      {"name": "Torre Huichol", "price": "$24.99", "category": "appetizer"},
      {"name": "Ceviche a La Riviera Nayarit", "price": "$18.99", "category": "appetizer"}
    ],
    "menu_url": "https://mariscoslarivieranayaritga.com/mariscoslarivieranayarit-norcross?utm_source=google/menu/mariscoslarivieranayarit-norcross",
    "reservation_url": null,
    "phone": "(770) 662-0086",
    "instagram": "mariscoslarivieranayarit",
    "dietary_options": [],
    "specials": [],
    "genres": [],
    "parking": []
  }
}
