{
  "venue_id": 4857,
  "venue_slug": "chefs-house-peking-duck",
  "venue_name": "Chef’s House - Peking Duck",
  "website": "https://chefshouseduluth.com/",
  "combined_text": "--- Main Page ---\nChef's House Peking Duck Duluth",
  "meta": {
    "og_image": "PUBLIC_URL%/chefducklogo.png",
    "meta_description": "Chef's House Peking Duck Restaurant, Best Cantonese Cuisine in Town.",
    "reservation_links": [],
    "menu_links": [],
    "instagram": null,
    "facebook_url": null,
    "phone": null
  }
}