{
  "venue_id": 4816,
  "venue_slug": "dave-poes-bbq",
  "venue_name": "Dave Poe's BBQ",
  "website": "https://davepoes.com/",
  "combined_text": "--- Main Page ---\nDave Poe's BBQ - Marietta\nmap marker pin\n660 Whitlock Avenue Southwest, Marietta,  30064\nAbout us\nHello from Dave Poe,\nMindy Hinkson and Zach Poe!\nServing authentic award-winning barbecue, located just west of the square in Marietta, our traditional 19th-century pit-cooked meals create the perfect Art of BBQ Experience!\nRead more\nabout us\nCatering\nThere's No Place Like Dave Poes!\nDave Poe's BBQ specializes in catering corporate events, civic affairs, church gatherings, rehearsal dinners, school functions and events of all types.\nCatering\nPrivate parties\nBook your next event with us!\nBook now\nReviews\nreview by Yelp\nRegina D:\nLiterally the best bbq on this side of town. Sometimes the chicken breast can be dried out but even with that they have the best Mac and cheese I've ever had and I love their bbq sauce. Gives you a real authentic down south vibe also.\nreview by Yelp\nKevin B:\nHard to find good BBQ where I live; Dave Poe's was super accommodating when I explained wanting to try out their different options.. great spot!! Reviews don't lie the Mac n cheese was fire!\nreview by Yelp\nLaura C:\nIncredibly impressed with Dave Poe's! About a 10 minute drive off the highway in a small strip mall.... definitely worth the drive. I had the beef brisket which was Fan-Freaking-Tastic! So tender and juicy...\nreview by Yelp\nSuzann S:\nI love this restaurant. The food is delicious. The mac and cheese is a star of the menu.   We went there for a curbside order and were especially pleased with the COVID precautions Dave's is taking. You just can't beat great food coupled with a caring staff and owner.\nreview by Yelp\nAsia I:\nOmg where do I start?! This is the best BBQ restaurant I've had so far in the 9 years I've lived in GA. The ribs, smoked wings, mac & cheese, collard greens, baked beans & potato salad were a-mazing!  I'm totally hooked now...\nStop reviews carousel\nPlay reviews carousel\nAtlanta's Best BBQ!\nOur Menu\nThere's No Place Like Dave Poes!\nBook a party\nLet Us Cater Your Next Event!\ncatering\nDot slide navigation number 1\nDot slide navigation number 2\nDot slide navigation number 3\nslideshow start stop playing\nNewsletter\nLocation\n660 Whitlock Avenue Southwest\nMarietta,\n30064\nHours\nThur, Fri, Sat\n11:00 AM - 7:30 PM\nMon, Tue, Wed\n11:00 AM - 3:00 PM\nFind us on...\nTwitter page\nFacebook page\nInstagram page\nYelp page\nContact us\n(770)-792-2272\nmindy@davepoes.com\nPowered by:\nWebsite design, Social Media marketing and Email marketing provided by SpotHopper.\n×\nNewsletter\n\n--- Page: /marietta-dave-poe-s-bbq-food-menu ---\nDave Poe's BBQ - Food Menu\nOur Menu\nMenu\nPlates\nIncludes: 2 sides and a piece of Texas toast. - add Brunswick stew for additional 50 cents\nPulled Pork\n$14.95/Reg\n$16.95/Lg\nBaby Back Ribs Plate\n$19.95/Lg\n1/2 Chicken Plate\n$11.95\nPulled Chicken\n$14.95/Reg\n$16.95/Lg\nBeef Brisket\n$16.95/Reg\n$19.95/Lg\nSt. Louis Cut Spare Ribs Plate\n$19.95/Lg\nSmoked Wings Plate\n$14.95/6 Pieces\nRedneck Lasagna\nRedneck Lasagna\n$3.50/Single\n$6.95/Pint\n$12.95/Quart\n$51.95/1/2 Pan\nDave's loaded mac & cheese over his Brunswick stew\nThe Special\nSandwich, one side, Lg drink\nThe Pork Special\n$11.95\nThe Chicken Special\n$11.95\nThe Brisket Special\n$12.95\nRibs\nBy the slab\nBaby Back Ribs\n$15.95/1/2 Slab\n$29.95/Full Slab\nFull/Half\nSt. Louis Cut Spare Ribs\n$15.95/1/2 Slab\n$29.95/Full Slab\nFull/Half\nSandwiches\nPulled Pork Sandwich\n$7.75/Reg\n$9.75/Lg\nBeef Brisket Sandwich\n$9.45/Reg\n$12.45/Lg\nPulled Chicken Sandwich\n$7.75/Reg\n$9.75/Lg\nBurgers\nAdd Cheese $0.60\nQuarter-Pound Burger\n$5.95\nAdd Cheese $.60\nHalf-Pound Burger\n$6.95\nAdd Cheese $.60\nHot Dog\n$4.75\nBBQ by the Pound\n1/2 Pound Pork\n$12.95\nPound Pork\n$20.95\n1/2 Pound Chicken\n$12.45\nPound Chicken\n$20.45\n1/2 Pound Beef Brisket\n$14.95\nPound Beef Brisket\n$26.95\nSmoked Wings\nWings\n$10.95/6\n$18.95/12\nChicken 1/2\n$7.95\nSides\nBaked Beans\n$3.50/Single\n$6.75/Pint\n$11.95/Quart\nCole Slaw\n$3.50/Single\n$6.75/Pint\n$11.95/Quart\nPotato Salad\n$3.50/Single\n$6.75/Pint\n$11.95/Quart\nCollard Greens\n$3.50/Single\n$6.95/Pint\n$12.95/Quart\nMac & Cheese\n$3.50/Single\n$6.95/Pint\n$12.95/Quart\n$51.95/Half-Pan\nOkra\n$3.50/Singe\n$6.95/Pint\n$12.95/Quart\nSingle/Pint/Quart\nGreen Beans\n$3.50/Single\n$6.95/Pint\n$12.95/Quart\nFrench Fries\n$3.50/Single\n$6.95/Pint\nTater Tots\n$3.50/Single\n$6.95/Pint\nOnion Rings\n$3.50/Pint\n$6.95/Basket\nPotato Chips\n$1.25\nTexas Toast\n$0.50/Reg\nBrunswick stew\n$3.25/Single\n$6.95/Pint\n$12.95/Quart\nBun\n$0.30/Reg\nJalapeño Cornbread\n$0.95/Reg\nPoe-Taters\nBaked Potato\n$3.95/Reg\nAdd Cheese $.75 | Add Chicken or Pork $9.95,  Add Brisket $10.95\nSalads\nHouse Salad\n$4.25\nAdd Pork or Chicken $9.95,  Add Brisket $10.95\nSeasonal\nSweet Potato Soufle\n$10.95/Quart\n$42.00/Basket\nBlack Eyed Peas\n$2.95/Single\n$6.50/Pint\n$10.95/Quart\nBrisket Chili\n$2.95/Single\n$6.50/Pint\n$10.95/Quart\nButternut Squash Soup\n$2.95/Single\n$6.50/Pint\n$10.95/Quart\nBBQ Sauce\nTraditional\n$1.50/6oz\n$3.75/Pint\n$6.95/Quart\nCarolina\n$1.50/6oz\n$3.75/Pint\n$6.95/Quart\nSpicy\n$1.50/6oz\n$3.75/Pint\n$6.95/Quart\nKids\n12 & Under | Includes a sandwich, KIDS drink and a side\nKids Piglet Pork Only\n$4.95\nKids Piglet Chicken Only\n$4.95\nKids Hot Dog Only\n$3.95\nKids Grilled Cheese Only\n$7.95\nKids Piglet Pork Meal\n$9.25\nKids Piglet Chicken Meal\n$9.25\nKids Grilled Cheese Meal\n$7.95\nKids Hot Dog Meal\n$8.95\nKids Drink\n$1.00\nSweets\nCookies\n$0.95\n$1.09\nMacademia Nut Cookie | Chocolate Chip Cookie\nFried Apple Pie\n$1.95\n$2.24\nBanana Pudding\n$2.95\n$3.39\nApple Cobbler\n$29.95/1/2 Pan\nPeach Cobbler\n$29.95/1/2 Pan\nMoon Pie\n$1.50/Single\nSauce\n$1.25/Single\n$2.95/Pint\n$4.95/Quart\n\n--- Page: /marietta-dave-poe-s-bbq-events ---\nDave Poe's BBQ - events\nEvents\nSt. Patrick's Day\nTuesday March 17th\nGrab your best green garb and join us for St. Patrick's Day!\n11:00 AM - 03:00 PM\n2026-03-17 11:00:00\n2026-03-17 15:00:00\nAmerica/New_York\nSt. Patrick's Day\nGrab your best green garb and join us for St. Patrick's Day!\nDave Poe's BBQ\nDave Poe's BBQ\nmindy@davepoes.com\n\n--- Page: /marietta-dave-poe-s-bbq-about ---\nDave Poe's BBQ - About\nDot slide navigation number 1\nDot slide navigation number 2\nDot slide navigation number 3\nDot slide navigation number 4\nDot slide navigation number 5\nslideshow start stop playing\nAbout us\nHello from Dave Poe,\nMindy Hinkson and Zach Poe!\nThe staff of Dave Poe's BBQ, located on Whitlock Avenue in Marietta, loaded up their trucks for Washington, DC on July 28 in order to serve their award-winning barbecue to members of the U.S. Senate. Each year, senators have the opportunity to showcase the best food in their states. Last week, Georgia Senator Johnny Isakson bestowed the honor upon David Poe and his crew of barbecue experts. Washington was not disappointed as the Russell building, which houses the senate offices, filled with the mouthwatering aroma of Atlanta's best BBQ. Positive comments floated down the hall as fast as the smell of the hickory-smoked pork. Although the intended guests included senators, military personnel and other officials, passersby flocked to the open doorway just to breathe in the tantalizing fragrance.\nWhen the senators arrived for the luncheon, no one could wait to dig in. As they filled their plates with hand-pulled pork and beef, creamy coleslaw, savory baked beans, one senator was overheard saying, \"This barbecue is even better than what we have in my home state.\" The wonderfully decadent macaroni and cheese was a favorite treat. The cheesy goodness even tempted one diminutive female senator to return for seconds and possibly even thirds. The warm reception Dave Poe's received in the nation's Capitol was also reflected in the 2009 Zagat survey. For the second year running, Dave Poe's earned the highest rating of \"Extraordinary to Perfection\" and best barbecue in Atlanta. In addition, Dave's was voted as having the \"best ribs\" in Access Atlanta's \"Best of the Big A\" survey.\nMost locals will not be surprised by the restaurant's positive reputation both here at home and nationally. Dave Poe has been slow smoking competition quality BBQ for the past 34 years. After only a few years in the business, he became the first Grand Champion of the Georgia State BBQ Championship. Since then, Dave has accumulated wins in numerous states up and down the East Coast. He has been preparing legendary slow-smoked, time honored competition barbecue since 1975. At that time, Dave co-founded the family catering business, Stump and Sons. Dave has catered barbecue parties for the majority of the Fortune 500 companies here in the Atlanta area and throughout the Southeast. Over the years, he has fed everyone from Charlie Daniels to Vince Dooley and everyone in between.\nDave Poe's BBQ specializes in catering corporate events, civic affairs, church gatherings, rehearsal dinners, school functions and events of all types. Locals can visit Dave Poe's BBQ at 660 Whitlock Avenue in Marietta to determine their own vote. Additional information is also available by calling\n(770)792-2272\nor on the web at\ndavepoes.com\n.\nContact us:\nby ",
  "meta": {
    "og_image": null,
    "meta_description": null,
    "reservation_links": [
      "https://tmt.spotapps.co/private-parties?spot_id=72194&callback_url=http://davepoes.com/"
    ],
    "menu_links": [
      "https://davepoes.com/marietta-dave-poe-s-bbq-food-menu",
      "https://davepoes.com/marietta-dave-poe-s-bbq-food-menu",
      "https://davepoes.com/marietta-dave-poe-s-bbq-food-menu"
    ],
    "instagram": "davepoes",
    "facebook_url": "https://www.facebook.com/136498713170513",
    "phone": "(770) 792-2272"
  }
}