{
  "venue_id": 1424,
  "venue_slug": "chiefs-on-broadway",
  "venue_name": "Chief's on Broadway",
  "venue_type": "bar",
  "menu_url": "https://www.chiefsonbroadway.com/food-menu",
  "menu_text": "--- Menu Page: https://www.chiefsonbroadway.com/food-menu ---\nChief’s Nashville | Food & Drink Menus + Hours\nSkip Navigation\n- Button will scroll to this section on the current page.\nMenus & Hours\nChoose a menu\nLunch & Dinner\nKids\nFriendly Shadows\nLunch & Dinner\nDaily: 11AM-10PM\nGF\nGluten Free\nV\nVegetarian\nVG\nVegan\nSnacks\nPork Belly Burnt Ends\nTender pieces of pork belly with caramelized Kathy's Sweet Sauce\nLoaded Chips\nCarolina Vinegar Chips loaded with choice of pulled pork or pulled chicken, Alabama White Sauce, Kathy's Sweet Sauce, queso, cheddar cheese, pico, scallions, and Serrano peppers\nSmoked Chicken Wings (6 or 12)\nGet’em dry rubbed or sauced! Sauces: Alabama White Sauce, Kathy’s Sweet Sauce Rod's Hot Sauce\nRiblets\nPit cooked spare ribs cut into bite-sized pieces\nSliders\nMix & Match Pack\n6 Mix & Match Sliders with choice of pulled pork, pulled chicken, brisket, or hot chicken\nSandwiches\nPulled Pork\nCarolina style whole hog mopped with Rodney’s Vinegar Pepper Sauce, served on a toasted bun Served Traditional Style or Southern Style with Kathy's Sweet Sauce and pickles - choice of 1 side\nPulled Chicken\nServed with Alabama White Sauce, on a toasted bun - choice of 1 side\nTurkey Breast\nSliced smoked turkey breast, served on a toasted bun with a side of Alabama White Sauce - choice of 1 side\nBrisket\nBrisket, served on a toasted bun (sliced upon request) - choice of 1 side\nClassic Griddle Burger\nTwo patties, white American cheese, lettuce, tomato, onions, and burger sauce\nPlates\nRod’s Original Whole Hog Plate\n8oz perfectly seasoned pit cooked whole hog - choice of 2 sides\nGF\n1/2 Chicken Plate\nChoice of 2 sides\nBrisket Plate\nServed sliced - choice of 2 sides\nGreens\nSouthern Chopped Salad\nChopped iceberg, bacon, cheddar cheese, hard boiled egg, cucumbers, grape tomatoes, red onions, and cornbread croutons, topped with your choice of pit cooked meat (whole hog, pulled chicken, turkey, brisket ($4)\nRodney's Hot Chicken\nRodney's Hot Chicken Tender Sandwich\nFried chicken tenders doused in Rodney's Hot Sauce, topped with cole slaw and served on a bun\n4 Piece Plate + 2 Sides\nHand breaded and fried to golden brown. Choose: Southern Style or Rod's Hot Sauce\nCombos\nTwo Meat Combo\nChoose 2: Whole hog, chicken, turkey brisket - choice of 2 sides\nThree Meat Combo\nChoose 3: Whole hog, chicken, turkey brisket - choice of 2 sides\nSides\nCrinkle Cut Fries\nV\nBaked Beans\nGF\nMac & Cheese\nV\nCollard Greens\nGF\nCole Slaw\nV\nGF\nPotato Salad\nV\nGF\nCornbread\nV\nCuke & Tomato Salad\nV\nBag of Skins\nDesserts\nElla's Banana Puddin'\nV",
  "meta": {}
}