{
  "venue_id": 2097,
  "venue_slug": "kpot-korean-bbq-hot-pot",
  "venue_name": "KPOT Korean BBQ & Hot Pot",
  "venue_type": "bar",
  "menu_url": "https://thekpot.com/menu/",
  "menu_text": "--- Menu Page: https://thekpot.com/menu/ ---\nKorean BBQ and Hot Pot Menu - KPOT\nKorean BBQ and Hot Pot Menu\nLunch\nJoin us for a flavorful lunch at KPOT, where you can enjoy our extensive Korean BBQ and Hot Pot menu, all served with fresh ingredients and bold flavors to satisfy your midday cravings. Plus, with quick service and ingredients ready to go, you won't spend your whole lunch break waiting.\nPrice Varies by Location\n\nAll-you-can-eat Korean BBQ or Hot Pot or both\n\nFreshly prepared ingredients\n\nUnlimited access to our Hot Bar & Sauce Bar\n\nComplimentary dessert and ice cream*\n*Dessert options may vary based on locations\nDinner\nGather your friends and family for an unforgettable dinner at KPOT, where Korean BBQ and hot pot come together for a fun, interactive dining experience filled with mouthwatering flavors and shared moments around the table. See our Korean BBQ and Hot Pot menus below!\nPrice Varies by Location\n\nAll-you-can-eat Korean BBQ or Hot Pot or both\n\nFreshly prepared ingredients\n\nUnlimited access to our Hot Bar & Sauce Bar\n\nComplimentary dessert and ice cream*\n\nPremium selections of meats and seafood\n*Dessert options may vary based on locations\nAll Korean BBQ and Hot Pot menu pricing options come with access to our hot appetizer and signature sauce bar. with over 70+ freshly prepared ingredients, get ready to craft the perfect sauce to compliment your meal.\nLearn How to Kpot\n*Korean BBQ and Hot Pot Offerings May Vary Based on Locations\nOur bar isn’t just a place to grab a drink—it’s where unforgettable nights begin! Whether you’re toasting with handcrafted cocktails, sipping on ice-cold beer, or exploring our curated selection of wines and spirits, there’s something for everyone.\nFind Your Location\n*Korean BBQ and Hot Pot Offerings May Vary Based on Locations\n×\nHome\nMenu\nOur Menu\nHow To Kpot\nLocations\nAbout Us\nAbout\nCareers\nFranchise\nPromotions\nPress\nShop\nGear\nGift Cards\nContact",
  "meta": {}
}