{
  "venue_id": 1633,
  "venue_slug": "southern-grist-brewing-germantown",
  "venue_name": "Southern Grist Brewing - Germantown",
  "venue_type": "bar",
  "menu_url": "http://www.southerngristbrewing.com/lbylauter",
  "menu_text": "--- Menu Page: http://www.southerngristbrewing.com/lbylauter ---\nL By Lauter — Southern Grist Brewing Co\n0\na food concept by southern grist brewing company\nHours:\nFull Menu Hours:\nThurs 4-9pm / Fri 2-9:30pm / Sat 11-9pm / Sun 11-7pm\nLimited Menu Hours:\nMon-Wed 12-9pm / Thursday 12-4pm / Fri 11-2pm\nMenu Updated: 12/19\nMENU\nGreen chili queso with pickled onion, Calabrian chili and tortilla chips   10\nCaesar Salad with smoked olive Caesar dressing, crunchy parmesan    14\nOmnivore style- add a burger patty  +4\nPollotarian style- add grilled smoked chicken  +3\nBLT with thick cut bacon, smoked Duke’s mayo, heirloom tomato, bib lettuce  14\nNations Burger with bacon, heirloom tomato, smoked mozzarella and smoked Duke’s  14\nBattered French Fries  8\nadd green chili queso + 4\nKids:\nThe Babysitter: includes coloring pages, crayons, popsicle, snack mix and apple juice | 5\nHappier Meal: kids cheese burger, fries, drink, coloring pages & crayons | 14\nExecutive Chef: Andrew Coins  |  Chef De Cuisine: Kenji Nakagawa\nCONSUMING RAW OR UNDERCOOKED MEATS, POULTRY, SEAFOOD, SHELLFISH OR EGGS MAY INCREASE YOUR RISK OF FOODBORNE ILLNESS.\nVisit Us\n5012 Centennial Blvd.\nNashville, TN 37209\nL By Lauter Hours:\nFull Menu Hours-\nThurs: 4-9pm\nFri & Sat: 11-9pm\nSun: 11-7pm\nLimited Menu Hours-\nMon-Wed: 12-9pm\nThurs: 12-4pm\nPhone\n615.864.7133\nPress\nFollow our journey.",
  "meta": {}
}