{
  "venue_id": 3728,
  "venue_slug": "uncle-jacks-alpharetta",
  "venue_name": "Uncle Jack's Meat House - Alpharetta",
  "venue_type": "restaurant",
  "menu_url": "https://unclejacksbayside.com/food-menu",
  "menu_text": "--- Menu Page: https://unclejacksbayside.com/food-menu ---\nUncle Jack's Steakhouse - Food Menu\nOur Menu\nMenu\nSoups & Appetizers\nPanamanian Jumbo Shrimp Cocktail\n$26.00\nMaryland Style Crab Cake\n$24.00\nOysters Jackefeller\n$28.00\nThick Cut Maple Glazed Bacon\n$23.00\nBaked Clams\n$23.00\nWagyu Kobe Meatballs\n$25.00\nLollipop Lamb Chops\n$28.00\nFrench Onion Soup\n$16.00\nCharred Spanish Octopus\n$27.00\nBacon Wrapped Shrimp\n$24.00\nLobster Bisque\n$26.00\nTuna Tartare 2 Ways\n$27.00\nSalads\nCaesar Salad\n$19.00\nRomaine, semolina croutons, shaved Reggiano Parmesan, and garlic Parmesan dressing.\nIceberg Wedge Salad\n$21.00\nRed onions, bacon, tomatoes, stilton blue cheese crumbles, and blue cheese dressing.\nOrganic Mesclun Salad\n$19.00\nTomatoes, goat cheese, roasted pine nuts, dried cranberries, dressing du jour.\nFresh Buffalo Mozzarella Tomato Salad\n$22.00\nOrganic greens, basil threads, balsamic reduction.\nLobster Avocado Salad\n$28.00\nHeirloom tomatoes, organic greens, sherry-mustard dressing.\nSteaks & Entrees\nPrime Filet Mignon\n$49.00/8 oz\n$64.00/12 oz\nServed in its own juices.\nBoneless NY Strip\n$37.00/8 oz\n$65.00/16 oz\nAll natural 21-day wet-aged, served in its own juices.\nPrime Rib Chop (Aka Fred Flintstone)\n$95.00/28oz\n35-day dry-aged long bone tomahawk chop.\nPorterhouse for Two\n$165.00\nFeatures both the filet and the New York strip cut.\nTomahawk Chop for Two\n$185.00\n35-day dry-aged, double long bone rib chop, charred and sliced off the bone.\nPorterhouse for Three\n$250.00\nFeatures both the filet and the New York strip cut.\nWagyu Strip\n$85.00/8oz\n$120.00/12oz\n$150.00/16oz\nPrime Bone - In Filet Mignon (Aka Boneyard)\n$74.00\nServed in its own juices.\nKobe Beef\n$150.00/8 oz\n$225.00/12oz\n$300.00/16oz\nRenowned for its rich marbling, buttery texture, and nutty flavor.\nPork Chop à la Jack\n$42.00\nCenter-cut pounded thinly, herb Parmesan crusted, vinegar, and hot cherry peppers.\nChicken ala Willie\n$36.00\nGrilled organic chicken breasts, wild mushroom medley, sun-dried tomatoes, scratch marsala gravy.\nSteak Frites\n$39.00\n8oz prime NY strip served with French fries and au poivre sauce on the side. Available at the Bar and Online Ordering only.\nSteak Burgers & Sandwiches\nThe Big Jack Burger\n$29.00\nAll natural, custom w.j.d. blend of prime beef, tomato bacon jam, American cheese, secret sauce, fries.\nThe Black Truffle Burger\n$39.00\nPrime dry-aged blend with shaved black truffles, gruyere cheese, red onion jam, black truffle herb butter (only served medium rare), fries.\nThe Wagyu Burger\n$35.00\nPrime wagyu beef blend, bacon jam, bone marrow butter, fries.\nJack's Steak Sandwich\n$34.00\nPrime NY strip steak, garlic bread with roasted onions, buffalo mozzarella, fries.\nJack's French Dip Sandwich\n$29.00\nHerb-crusted shaved prime rib steak, Grande mozzarella, French onion soup, fries.\nSeafood\nYellowfin Tuna\n$39.00\nSesame crusted, mixed green seaweed salad, scallions, pickled red onions, asian dressing, wasabi.\nAtlantic Salmon\n$38.00\nGrilled, toasted farm greens, champagne-dijon sauce, dried citrus gremolata.\nChilean Seabass\n$45.00\nLobster Tail\n$60.00/10 oz\nButters & Add - Ons\nRoasted Garlic & Herb Butter\n$5.00\nBlack Truffle Butter\n$10.00\nBacon & Maytag Blue Cheese\n$12.00\nGrilled Shrimp\n$21.00/5 pcs\nLobster Tail\n$60.00/10 oz\nCrab Oscar\n$25.00\nChicken\n$12.00\nSteak\n$26.00\nSalmon\n$19.00\nTuna\n$21.00\nGrated Black Truffle\n1/4 oz $50.00 | 1/2 oz $100.00 | 1 oz $150.00\nSides\nGarlic Mashed Potato\n$14.00\nSteak Fries\n$12.00\nBaked Potato\n$10.00\nSteamed or Sauteed Broccoli\n$12.00\nSauteed Onions\n$12.00\nCreamed Spinach\n$12.00\nSweet Potato Fries\n$12.00\nHandcut in-house.\nLoaded Baked Potato\n$18.00\nSauteed Mushrooms\n$14.00\nBrussels Sprouts\n$15.00\nIncludes bacon bits.\nFrench Fries\n$10.00\nAsparagus\n$15.00\nFive Cheese Mac\n$15.00\nBacon Corn Brulee\n$15.00\nTruffle Parm Fries\n$15.00\nSauces\nTop Shelf Au Poivre\n$5.00\nHollandaise\n$5.00\nBlack Truffle Butter\n$10.00\nBlack Peppercorn Sauce\n$5.00\nBearnaise\n$5.00\nDesserts\nNew York Cheesecake\n$16.00\nBanana Cream Pie\n$16.00\nChocolate Soufflé Cake\n$16.00\nApple Strudel\n$16.00\nChocolate Mousse\n$16.00\nTiramisu\n$16.00\nPecan Pie\n$16.00\nPistachio Cake\n$16.00\nFresh Fruit\n$16.00\nVanilla Ice Cream\n$10.00\nPistachio Ice Cream\n$10.00\nKids\nKids Chicken Tenders\n$15.00\nKids Pasta\n$15.00\nKids Burger\n$15.00\nKids Mac\n$15.00",
  "meta": {}
}