{
  "venue_id": 2502,
  "venue_slug": "old-lady-gang",
  "venue_name": "Old Lady Gang",
  "website": "https://www.oldladygang.com/",
  "combined_text": "--- Main Page ---\nOld Lady Gang | A Southern Eatery\nLeave this field empty if you're human:\nDiscover\nOUR STORY\nJoyce Jones\n,\nBertha Jones\n&\nNora Wilcox\nare the original OLG’s. If there’s one thing that you don’t have to question, when it comes to these three firecrackers, is that family truly comes first as far as they’re concerned. They’re three enthusiastic sisters from Atlanta, Georgia that certainly know their way around a kitchen.\nREAD MORE\nview our menu\nThe Old Lady Gang promises to deliver good old fashioned southern cuisine made with love. Browse below or\nCLICK HERE\nto view our full menu selection.\nDRINKS\nENTREES\nSTARTERS\nDESSERT\nSIDES\nVIEW FULL MENU\nOur menu is subject to change without notice. If you have questions about an item please contact us ahead of time. Additionally, we know mistakes can happen, & we are always happy to correct any errors made by our staff. Food that is prepared correctly may NOT be returned. This applies to everything, from spicy dishes to cocktails. If you have a sensitive palate, please let your server know.\nWanted\nFOR THE BEST\nthe olg experience\nSecond only to the incredible food is our atmosphere at Old Lady Gang. Located in Atlanta, GA’s historic Castleberry Hill, this multi-level dining and entertainment complex, complete with two full bars and outdoor patio has a style that’s all its own.\nGO INSIDE\nHost\nYOUR EVENT\nAt the Old Lady Gang, there’s a space for every occasion. From the private dining room, and the performance stage, to the outdoor patio. Your guests will be thrilled as you bring your event to life at OLG. Contact us today and a representative will contact you to discuss hosting your private event with us.\nCONTACT US\nCopyright All Rights Reserved © 2025\n\n--- Page: /menu ---\nMenu | Old Lady Gang\nOUR MENU\nPlease enjoy your time with us! 18% gratuity is included on all checks.\nWe know mistakes can happen, & we are always happy to correct any errors made by our staff. However, food & drinks that are prepared according to our recipe may NOT be returned. This applies to everything, from spicy dishes to cocktails. Please inform your server if you have a sensitive palate!\nKIDS MENU AVAILABLE UPON REQUEST\nDrinks\nBottled Beer Offerings\n$\n8\nStella | Blue Moon | Red Stripe | Corona | Yuengling | Sweetwater 420 | Bud Light | Michelob Ultra | Redd’s Apple Ale | Heineken | Budweiser | Coors Light | Guinness | Cutwater (variety flavors)\nJuice\n$\n5\n$5 for 8oz pour and $2.50 to add 4oz to a spirit\nOther Beverages\nbottled sparkling or flat water, soft drinks, sweet tea\nRed (Wine)\nPinot Noir, Noble Wines 9/31\nMalbec, Septima 10/35\nMerlot, Tunnel of Elms 8/27\nCabernet, Tunnel of Elms 8/27\nSparkling / Rose / Whites (Wines)\nProsecco, Cupcake 9/31\nRiesling, Chateau Ste. Michelle 10/35\nMoscato, Piquitos 10/35\nChardonnay, Tunnel of Elms 8/27\nPinot Grigio, Tunnel of Elms 8/27\nOLG Craft Bar\nAunt Nora’s Sneaky Georgia Peach\n$\n15\nvodka, peach schnapps, peach, pineapple juice\nBlue Tini\n$\n14\nClock That Tea!\n$\n15\nTitos Vodka, Sweet and Sour, Sweet Tea\nKaela’s Spiked Lemonade\n$\n15\nlemon vodka, triple sec, fresh lemon juice, topped with sprite\nMargarita Flights\n$\n10\nMomma Joyce’s House Punch\n$\n13\ncoconut rum, peach schnapps, strawberry, pineapple juice, orange juice\nOLG Reggae\n$\n14\ncoconut rum, strawberry, pineapple & orange juice, banana liqueur, topped with blue curacaos, and 151 rum\nOLG Strawberry Margarita\n$\n17\nhennessy, fresh strawberries, agave, sweet & sour, lime juice\nStubborn Atlanta Mule\n$\n15\ncognac, vodka, lime juice, topped with ginger beer\nThe Housewife\n$\n14\npatron, fresh lemon & lime, triple sec, agave, topped with soda\nTodd’s Margarita\n$\n16\ndon julio, grand mariner, agave, sweet & sour, lime juice\nSTARTERS\nThe perfect start to a great meal begins here.\nStarters\nFried Green Tomatoes\n$\n13\ntopped with pulled bbq chicken and feta cheese.\nTodd’s Crispy Salmon Bites\n$\n15\ndeep fried salmon bites, served with our house-made cajun remoulade\nDeep Fried Whipped Deviled Eggs\n$\n12\ntopped with crispy brown sugar bacon + add grilled shrimp for $5.\nOLG Signature Wings\n$\n15\n5 wings fried then grilled, tossed in OLG hot sauce.\nMama Sharon’s Seared Crabcake\n$\n14\nfresh lump crab, served with mango salsa and remoulade\nSOUTHERN FAVORITES & ENTREES\nBig flavor in every bite. Our entrees are as delicious as they are diverse.\nEntrees\n(Limited Availability) Blaze’s Amazing Turkey Wings\n$\n25\nServed with 2 sides\nBig Lamb Dinner\n$\n32\nServed with side of mashed potatoes\nMama Joyce’s BBQ Rib Tips\n$\n24\nserved with smashed potatoes and green beans\nKandi’s Original Baked Chicken\n$\n24\n(limited availability) served with dark meat and choice of 2 sides\n* Now offering dark meat only\nFried Fish Dinner\n$\n28\nDeep Fried Fish served with collard greens and mac & cheese\n* OLG Chee",
  "meta": {
    "og_image": "https://oldladygang.com/wp-content/uploads/2017/03/olg-social-cover-1.jpg",
    "meta_description": "The Old Lady Gang promises to deliver its patrons good old fashioned southern cuisine prepared with love. Make your reservation today!",
    "reservation_links": [],
    "menu_links": [
      "https://oldladygang.com/menu/",
      "https://oldladygang.com/menu/",
      "https://oldladygang.com/menu",
      "https://oldladygang.com/menu/#drinks",
      "https://oldladygang.com/menu/#entrees",
      "https://oldladygang.com/menu/#starters",
      "https://oldladygang.com/menu/#dessert",
      "https://oldladygang.com/menu/#entrees",
      "https://oldladygang.com/menu"
    ],
    "instagram": "oldladygang",
    "facebook_url": "http://facebook.com/oldladygang",
    "phone": "(404) 748-9689"
  }
}