{
  "venue_id": 4647,
  "venue_slug": "velvet-taco-buckhead",
  "venue_name": "Velvet Taco",
  "website": "https://www.velvettaco.com",
  "combined_text": "--- Main Page ---\nYou've Never Had a Taco Like This | Velvet Taco\nGet the Mobile App\nBeginning of dialog window. It begins with a heading 1 called 'Get the Mobile App'. Escape will close the window.\npress enter or escape to dismiss this modal\nDownload our app for the best prices and taco perks!\nGet\nthe app now\nHome Carousel\nNorth Hills Now Open. 4208 Six Forks Rd, Suite 150 Raleigh, NC 27609. 919-867-4667. Hours: Sun-Thurs 11am to 11pm, Fri, Sat 11am to 12am\nVisit Us\nWTF Me - do it weekly\nOrder Online\nSee Lineup\nCater boldly\nOrder Pickup\nOrder Delivery*\nThe Velvet Room\nLearn More\nA funky taco spot creating\ninternational flavors.\nWe’ve made it our mission to deliver a fresh take on the ubiquitous taco – to elevate this humble food to something more. We use a tortilla as a canvas to make our art. The result is over twenty different taco varieties featuring globe-trotting flavors. See our gallery of tacos to find what flavors await. We assure you that you’ve never had a taco like this.\nvelvettaco\nFollow the tacos\nbestieeee let’s go, we’re getting $5 margs.\n🚨$5 MARGS 🚨HAPPY #NATIONALMARGARITA DAY TO A\nfresssssssssssh #seriouslyscratchmade\n$5 margs... tell a friend to tell a friend 😮\nL\nit’s been a looooong week, you deserve a marg. A\ntequila lime chicken WTF 🤝 #NationalMargaritaDa\ntreat yourself 🫶 #NationalMargaritaDay is comin\ndid you know it actually takes our team 22 hours t\nRALEIGH YOU ALL KNOW HOW TO SHOW UP!!!! ✨ come t\nsoaked. it’s tikka Tuesday which means $3.75 Tik\nwe’re taking winter arc seriously over here. are\nFollow on Instagram\nLeaving velvettaco.com\nBeginning of dialog window. It begins with a heading 1 called Leaving velvettaco.com. Escape will close the window.\nYou are about to leave Velvet Taco's website and enter partner-hosted website. The partner is an independent entity that provides services to Velvet Taco and our guests. When you leave www.velvettaco.com, you will be subject by the privacy and terms policies of the partner's website.\nTo continue to the website, click \"Accept\"\nIf you want to stay on Velvet Taco's website, click \"Cancel\".\nAccept\nand continue to third party site. Opens in new window\nCancel\nand return to The Velvet Taco site\npress enter or escape to dismiss modal\n\n--- Page: /menu ---\nVelvet Taco Menu | Tacos, Bowls, Sides & Drinks | Fresh Ingredients and Globally Inspired Flavors\nGet the Mobile App\nBeginning of dialog window. It begins with a heading 1 called 'Get the Mobile App'. Escape will close the window.\npress enter or escape to dismiss this modal\nDownload our app for the best prices and taco perks!\nGet\nthe app now\nVelvet Taco Menu\nTacos\nVelvet\nBowls\nSides & Cake\nBoozy\nLibations\nKids\nBackdoor\nChicken\nTacos\ncustomize it\nswap tortilla for lettuce wrap\nWTFs\nCHICK\nBEEF\nPORK\nSEA\nVEG\nWeekly Taco Feature (Marketing)\nA bold new taco every week\nCheck out this month’s lineup\nTequila Lime Chicken\n2/18 - 2/24\ntequila lime chicken, black beans, roasted corn pico, avocado crema, queso fresco, buttered cilantro basmati rice, mixed cheese, seasoned tortilla strips, flour tortilla\nChick Tacos\nSpicy tikka chicken\nFan Favorite\n(FF)\ncrisp tenders, spicy tikka sauce, buttered cilantro basmati rice, raita crema, Thai basil, flour tortilla\n420 cal.\nBuffalo chicken\ncrisp tenders, house buffalo sauce, carrots, bleu cheese, ranch crema, flour tortilla\n390 cal.\nRotisserie chicken\nqueso blanco, roasted corn pico, charred tomato poblano salsa, cilantro, flour tortilla\n330 cal.\nChicken & waffle\ncrisp tenders, peppered bacon, peppercorn gravy, green apple slaw, maple syrup, red chile aioli, scallions, waffle tortilla\n490 cal.\nBeef Tacos\nSlow roasted angus brisket\nbarbacoa style, red chile mayo, avocado corn pico, queso blanco, micro cilantro, comté cheese encrusted flour tortilla\n510 cal.\nGrilled steak\n*\nportobello mushrooms, queso blanco, crispy red onion, Mexican oregano, corn tortilla\n330 cal.\nChimichurri steak*\n*\ngrilled flank steak, buttered cilantro basmati rice, chimichurri, avocado, pickled fresnos, queso fresco, cilantro, flour tortilla\n380 cal.\nBacon smash burger\n*\nFan Favorite\n(FF)\npeppered bacon, smoked cheddar, lettuce, onion, tomato, pickles, velvet sauce, flour tortilla\n390 cal.\nPork Tacos\nQuesa birria pork duo\n(GF)\n†\nFan Favorite\n(FF)\nslow-roasted pulled pork, gruyere cheese, queso listo, pickled red onion, cilantro, griddled corn tortillas, birria consomé for dipping\n600 cal.\nKorean fried rice\nslow-roasted pulled pork, gochujang egg fried rice, red chile aioli, pickled red onion, jalapenos, grilled pineapple, cilantro, flour tortilla\n420 cal.\nSea Tacos\nMexi-Cali shrimp\nFan Favorite\n(FF)\nblackened shrimp, napa slaw, sriracha aioli, avocado, roasted corn pico, micro cilantro, flour tortilla\n280 cal.\nGrilled salmon\n(GF)\n*\n†\nnapa slaw, citrus lime crema, pickled fresnos, roasted corn pico, avocado crema, micro cilantro, corn tortilla\n220 cal.\nFish n' chips\nbeer battered cod, curry aioli, french fries, malt vinegar, napa slaw, flour tortilla\n350 cal.\nVeg Tacos\nBeer battered cauliflower\n(V)\nFan Favorite\n(FF)\nqueso blanco, sabor hot sauce, avocado, roasted corn pico, candied pepitas, flour tortilla\n300 cal.\nFried paneer cheese\n(V)\ntomato chutney, tikka sauce, raita crema, Thai basil, flour tortilla\n320 cal.\nNashville hot tofu\n(V)\ncrispy tof\n\n--- Page: /about-us ---\nAbout Us | Tacos Without Borders | Velvet Taco\nGet the Mobile App\nBeginning of dialog window. It begins with a heading 1 called 'Get the Mobile App'. Escape will close the window.\npress enter or escape to dismiss this modal\nDownload our app for the best prices and taco perks!\nGet\nthe app now\nHome Carousel\nA funky taco spot creating\ninternational flavors.\nVelvet Taco is a temple to the liberated taco. We’re a one-of-a-kind taco concept serving premium food in a unique & funky fast-casual setting. Founded on the idea that tacos don’t have to be associated with Tex-Mex cuisine and can be made with the same care and quality ingredients as fine dining, Velvet Taco is where “anything goes meets the art of the possible.”\nSome cool things about us: we use only the freshest ingredients available to offer a menu that explores the edge of multi-cultural boundaries, liberating tacos to a whole new level. We slow roast our own chicken and corn, use lots of booze in our margaritas, and make everything from scratch. Which means our food tastes really awesome.\nOur tacos may not change the entire world, but we think they’re pretty freakin’ great.\nFollow\nThe Tacos\nfacebook\ninstagram\nlinkedin\nyoutube\ntiktok\nLeaving velvettaco.com\nBeginning of dialog window. It begins with a heading 1 called Leaving velvettaco.com. Escape will close the window.\nYou are about to leave Velvet Taco's website and enter partner-hosted website. The partner is an independent entity that provides services to Velvet Taco and our guests. When you leave www.velvettaco.com, you will be subject by the privacy and terms policies of the partner's website.\nTo continue to the website, click \"Accept\"\nIf you want to stay on Velvet Taco's website, click \"Cancel\".\nAccept\nand continue to third party site. Opens in new window\nCancel\nand return to The Velvet Taco site\npress enter or escape to dismiss modal\n\n--- Page: /location/north-hills/ ---\nLocations | Get the Best Tacos in North Hills delivered! | Velvet Taco\nGet the Mobile App\nBeginning of dialog window. It begins with a heading 1 called 'Get the Mobile App'. Escape will close the window.\npress enter or escape to dismiss this modal\nDownload our app for the best prices and taco perks!\nGet\nthe app now\nNorth Hills\nLocation Info\nNorth Hills\n4208 Six Forks Rd, Suite 150 Raleigh, North Carolina 27609\nAddress\n4208 Six Forks Rd, Suite 150 Raleigh, North Carolina 27609\nTelephone\n(919) 867.4667\nHours\nDays\nHours\nMon - Thur\n11am - 11pm\nFri - Sat\n11am - 12am\nSun\n11am - 11pm\nOrder Online\nDirections\nView Menu\nCatering\nCheck out our “WTF” Weekly Taco Feature\nPrint Menu\nPrices and items vary at participating locations. To find pricing and menu offerings,\nvisit our online ordering site here\n.\nNew\nVelvet Bowls\nSpicy tikka chicken bowl\nFan Favorite\n(FF)\ncrisp tenders or rotisserie chicken, spicy tikka sauce, raita crema, marinated red cabbage, cucumber, Thai basil, buttered cilantro basmati rice\n|\n500-970 cal.\nRotisserie chicken\n(GF)\n†\nor steak* bowl\nrotisserie chicken or grilled steak, queso blanco, roasted corn pico, black beans, guacamole, avocado crema, charred tomato poblano salsa, cilantro, buttered cilantro basmati rice\n|\n720 - 1040 cal.\nSlow-roasted angus brisket bowl\nbarbacoa style brisket, queso blanco, roasted corn pico, black beans, guacamole, red chile aioli, comté cheese tortilla halves, micro cilantro, buttered cilantro basmati rice\n|\n1090-1410 cal.\nSeasonal veggie bowl\n(V)\n(GF)\n†\nseasonal roasted veggies, guacamole, roasted corn pico, avocado crema, pickled onion, queso blanco, napa slaw, buttered cilantro basmati rice\n|\n630 - 1040 cal.\nMexi-Cali shrimp bowl\n(GF)\n†\nFan Favorite\n(FF)\nblackened shrimp, napa slaw, roasted corn pico, sriracha aioli, guacamole, micro cilantro, buttered cilantro basmati rice\n|\n460-870 cal.\nSay What?! Combo\nAny two tacos*, an individual side item, and a fountain beverage.\nSide options include your choice of queso, elote, guac, rice, or salsa\n*may exclude some WTFs\nChick Tacos\nSpicy tikka chicken\nFan Favorite\n(FF)\ncrisp tenders, spicy tikka sauce, buttered cilantro basmati rice, raita crema, Thai basil, flour tortilla\n|\n420 cal.\nBuffalo chicken\ncrisp tenders, house buffalo sauce, carrots, bleu cheese, ranch crema, flour tortilla\n|\n390 cal.\nRotisserie chicken\nqueso blanco, roasted corn pico, charred tomato poblano salsa, cilantro, flour tortilla\n|\n330 cal.\nChicken & waffle\ncrisp tenders, peppered bacon, peppercorn gravy, green apple slaw, maple syrup, red chile aioli, scallions, waffle tortilla\n|\n490 cal.\nVeg Tacos\nBeer battered cauliflower\n(V)\nFan Favorite\n(FF)\nqueso blanco, sabor hot sauce, avocado, roasted corn pico, candied pepitas, flour tortilla\n|\n300 cal.\nFried paneer cheese\n(V)\ntomato chutney, tikka sauce, raita crema, Thai basil, flour tortilla\n|\n320 cal.\nNashville hot tofu\n(V)\ncrispy tofu, napa slaw, ranch crema, house brined pickles, flour tortilla\n|\n400 cal.\nPork Tacos\nQuesa birria pork duo\n(GF)\n†\n",
  "meta": {
    "og_image": "https://velvettaco.b-cdn.net/wp-content/uploads/2024/09/vt_tacos_og_image_mobile.jpg",
    "meta_description": "Dine-In, Delivery & Take-Out Available! Featuring a variety of globally inspired tacos made in-house with fresh local ingredients and bold flavors.",
    "reservation_links": [],
    "menu_links": [
      "https://www.velvettaco.com/menu/",
      "https://www.velvettaco.com/menu/"
    ],
    "instagram": "velvettaco",
    "facebook_url": "https://facebook.com/velvettaco",
    "phone": "(919) 867-4667"
  }
}